aq/__init__.py
aq/graphapi.py
aq/login.py
aq/token.py
aq/auth_landing_pages/fail.html
aq/auth_landing_pages/handle-response.html
aq/auth_landing_pages/ok.html
aq/cli/__init__.py
aq/cli/__main__.py
aq/cli/commands/__init__.py
aq/cli/commands/get.py
aq/cli/commands/help.py
azure_query-0.0.4.data/scripts/aq
azure_query-0.0.4.dist-info/LICENSE
azure_query-0.0.4.dist-info/METADATA
azure_query-0.0.4.dist-info/WHEEL
azure_query-0.0.4.dist-info/top_level.txt
azure_query-0.0.4.dist-info/RECORD
