Metadata-Version: 2.1
Name: azure-query
Version: 0.0.4
Summary: Command Line utility to query Azure AD
Home-page: https://github.com/jjulien/azure-query
Author: John Julien
Author-email: john@julinfamily.com
License: UNKNOWN
Platform: UNKNOWN
Classifier: Programming Language :: Python :: 3
Classifier: License :: OSI Approved :: MIT License
Classifier: Operating System :: MacOS :: MacOS X
Requires-Dist: PyJWT
Requires-Dist: requests
Requires-Dist: cryptography
Requires-Dist: six
